mildom_dl/__init__.py
mildom_dl/__main__.py
mildom_dl/command.py
mildom_dl/mildomDL.py
mildom_dl-0.0.3.data/scripts/mildomDL.py
mildom_dl-0.0.3.dist-info/LICENSE
mildom_dl-0.0.3.dist-info/METADATA
mildom_dl-0.0.3.dist-info/WHEEL
mildom_dl-0.0.3.dist-info/entry_points.txt
mildom_dl-0.0.3.dist-info/top_level.txt
mildom_dl-0.0.3.dist-info/RECORD
