Metadata-Version: 2.1
Name: mildom-dl
Version: 0.0.3
Summary: "Command-line program to download videos from Mildom.com"
Home-page: https://github.com/NDSlib/mildom-dl
Author: hirossan4049
License: MIT
Platform: UNKNOWN
